Metadata-Version: 2.4
Name: bonsai-prp
Version: 1.4.0
Summary: Pipline result processing program for the JASEN pipeline and Bonsai tool.
Author-email: Markus Johansson <markus.h.johansson@skane.se>, Ryan Kennedy <Ryan.Kennedy@skane.se>
Project-URL: Repository, https://github.com/Clinical-Genomics-Lund/
Project-URL: Issues, https://github.com/Clinical-Genomics-Lund/bonsai-prp/issues
Project-URL: Changelog, https://github.com/Clinical-Genomics-Lund/CHANGELOG.md
Classifier: Development Status :: 3 - Alpha
Classifier: Natural Language :: English
Classifier: Operating System :: OS Independent
Classifier: Programming Language :: Python
Classifier: Programming Language :: Python :: 3.10
Classifier: Programming Language :: Python :: 3.11
Classifier: Programming Language :: Python :: 3.12
Requires-Python: >=3.10
License-File: LICENSE
Requires-Dist: setuptools
Requires-Dist: wheel
Requires-Dist: click==8.1.7
Requires-Dist: pydantic
Requires-Dist: pandas==2.1.3
Requires-Dist: numpy==1.26.3
Requires-Dist: Biopython==1.83
Requires-Dist: cyvcf2==0.31.1
Requires-Dist: pysam==0.22.1
Requires-Dist: pyyaml==6.0.2
Requires-Dist: requests==2.32.3
Provides-Extra: dev
Requires-Dist: pylint~=3.0.2; extra == "dev"
Requires-Dist: black~=23.11.0; extra == "dev"
Requires-Dist: isort~=5.12.0; extra == "dev"
Provides-Extra: test
Requires-Dist: pytest-cov~=4.1.0; extra == "test"
Requires-Dist: mypy==1.13.0; extra == "test"
Dynamic: license-file
